Metadata-Version: 2.4
Name: resemble-perth
Version: 1.0.0
Summary: Audio Watermarking and Detection Library
Home-page: https://github.com/resemble-ai/Perth
Author: Resemble AI, Aditya
Author-email: team@resemble.ai, aditya@resemble.ai
Project-URL: Bug Reports, https://github.com/resemble-ai/Perth/issues
Project-URL: Source, https://github.com/resemble-ai/Perth
Project-URL: Documentation, https://github.com/resemble-ai/Perth/blob/main/README.md
Keywords: Audio Watermarking,Perceptual Watermarking,Neural Networks,Audio Processing
Classifier: Programming Language :: Python :: 3
Classifier: Programming Language :: Python :: 3.8
Classifier: Programming Language :: Python :: 3.9
Classifier: Programming Language :: Python :: 3.10
Classifier: Programming Language :: Python :: 3.11
Classifier: License :: OSI Approved :: MIT License
Classifier: Operating System :: OS Independent
Classifier: Topic :: Multimedia :: Sound/Audio
Classifier: Topic :: Scientific/Engineering :: Artificial Intelligence
Requires-Python: >=3.8
License-File: LICENSE
Dynamic: author
Dynamic: author-email
Dynamic: classifier
Dynamic: description
Dynamic: description-content-type
Dynamic: home-page
Dynamic: keywords
Dynamic: license-file
Dynamic: project-url
Dynamic: requires-python
Dynamic: summary
